Metadata-Version: 2.1
Name: MsTeamsConnector
Version: 0.1.6
Summary: UNKNOWN
Home-page: https://pypi.org/project/MsTeamsConnector/
Author: Kirill Kravchenko
Author-email: 
License: MIT
Platform: UNKNOWN
